drd/__init__.py
drd/_version.py
drd/datasets/__init__.py
drd/datasets/download_utils.py
drd/datasets/eleven_sandstones.py
drd/datasets/icl_microct_sandstones_carbonates_2015.py
drd/datasets/icl_sandstones_carbonates_2009.py
drd/datasets/utils.py
drd-0.1.2.dist-info/LICENSE
drd-0.1.2.dist-info/METADATA
drd-0.1.2.dist-info/WHEEL
drd-0.1.2.dist-info/top_level.txt
drd-0.1.2.dist-info/RECORD
